Metadata-Version: 2.1
Name: NHentai-API
Version: 9.9.9
Summary: Enma is a Python library designed to fetch manga and doujinshi data from many sources.
Home-page: https://github.com/AlexandreSenpai/Enma
Author: AlexandreSenpai
Author-email: alexandrebsramos@hotmail.comW
License: LICENSE
Classifier: Programming Language :: Python :: 3
Classifier: License :: OSI Approved :: MIT License
Classifier: Operating System :: OS Independent
Requires-Python: >=3.9
Requires-Dist: requests ==2.31.0
Requires-Dist: beautifulsoup4 ==4.10.0
Requires-Dist: pydantic ==2.5.3
